hvpdb_tools/__init__.py
hvpdb_tools/bench.py
hvpdb_tools-0.1.0.dist-info/METADATA
hvpdb_tools-0.1.0.dist-info/WHEEL
hvpdb_tools-0.1.0.dist-info/entry_points.txt
hvpdb_tools-0.1.0.dist-info/top_level.txt
hvpdb_tools-0.1.0.dist-info/RECORD
