Metadata-Version: 2.4
Name: hvpdb-tools
Version: 0.1.0
Summary: Developer Tools & Debugging Plugin for HVPDB
Requires-Dist: hvpdb
Dynamic: requires-dist
Dynamic: summary
